fairml_datasets/__init__.py
fairml_datasets/__main__.py
fairml_datasets/collection.py
fairml_datasets/collections.py
fairml_datasets/dataset.py
fairml_datasets/datasets.py
fairml_datasets/file_handling.py
fairml_datasets/metadata.py
fairml_datasets/scenario.py
fairml_datasets/transform.py
fairml_datasets/data/__init__.py
fairml_datasets/data/final/annotations.csv
fairml_datasets/processing/__init__.py
fairml_datasets/processing/annotations.py
fairml_datasets/processing/datasets.py
fairml_datasets/processing/helpers.py
fairml_datasets/processing/scripts/_example.py
fairml_datasets/processing/scripts/communities.py
fairml_datasets/processing/scripts/communities_unnormalized.py
fairml_datasets/processing/scripts/compas_2_years.py
fairml_datasets/processing/scripts/compas_train_test_val_csv.py
fairml_datasets/processing/scripts/creditcard.py
fairml_datasets/processing/scripts/drug.py
fairml_datasets/processing/scripts/folktables_acsemployment.py
fairml_datasets/processing/scripts/folktables_acsemployment_small.py
fairml_datasets/processing/scripts/folktables_acsincome.py
fairml_datasets/processing/scripts/folktables_acsincome_small.py
fairml_datasets/processing/scripts/folktables_acsmobility.py
fairml_datasets/processing/scripts/folktables_acsmobility_small.py
fairml_datasets/processing/scripts/folktables_acspubliccoverage.py
fairml_datasets/processing/scripts/folktables_acspubliccoverage_small.py
fairml_datasets/processing/scripts/folktables_acstraveltime.py
fairml_datasets/processing/scripts/folktables_acstraveltime_small.py
fairml_datasets/processing/scripts/generate_synthetic_data.py
fairml_datasets/processing/scripts/german_credit.py
fairml_datasets/processing/scripts/german_credit_numeric.py
fairml_datasets/processing/scripts/german_credit_onehot.py
fairml_datasets/processing/scripts/hmda.py
fairml_datasets/processing/scripts/lipton_synthetic_hiring_dataset.py
fairml_datasets/processing/scripts/meps_panel_19_fy2015.py
fairml_datasets-0.1.4.dist-info/licenses/LICENSE-2.md
fairml_datasets-0.1.4.dist-info/licenses/LICENSE.md
fairml_datasets-0.1.4.dist-info/METADATA
fairml_datasets-0.1.4.dist-info/WHEEL
fairml_datasets-0.1.4.dist-info/top_level.txt
fairml_datasets-0.1.4.dist-info/RECORD
