Metadata-Version: 2.4
Name: fairml-datasets
Version: 0.1.4
Summary: A package for managing and processing datasets for fairness research in machine learning
License: CC BY 4.0
Requires-Python: >=3.10
License-File: LICENSE-2.md
License-File: LICENSE.md
Requires-Dist: aif360>=0.6.1
Requires-Dist: click>=8.1.7
Requires-Dist: fastparquet>=2024.11.0
Requires-Dist: folktables>=0.0.12
Requires-Dist: rich>=13.9.4
Requires-Dist: scikit-learn>=1.5.2
Requires-Dist: scipy>=1.14.1
Provides-Extra: test
Requires-Dist: pytest; extra == "test"
Requires-Dist: ruff; extra == "test"
Provides-Extra: docs
Requires-Dist: mkdocs; extra == "docs"
Requires-Dist: mkdocs-material; extra == "docs"
Requires-Dist: mkdocstrings[python]; extra == "docs"
Requires-Dist: mkdocs-click; extra == "docs"
Dynamic: license-file
